funmodel/__init__.py
funmodel/core/__init__.py
funmodel/core/predict/__init__.py
funmodel/core/predict/base.py
funmodel/core/predict/image.py
funmodel/utils/__init__.py
funmodel/utils/predictor.py
funmodel/utils/capture/__init__.py
funmodel/utils/capture/queue.py
funmodel/utils/image/__init__.py
funmodel/utils/image/transform.py
funmodel-0.0.9.dist-info/LICENSE
funmodel-0.0.9.dist-info/METADATA
funmodel-0.0.9.dist-info/WHEEL
funmodel-0.0.9.dist-info/top_level.txt
funmodel-0.0.9.dist-info/RECORD
