Metadata-Version: 2.1
Name: funmodel
Version: 0.0.9
Summary: funmodel
Home-page: https://github.com/farfarfun/funmodel
Author: bingtao
Author-email: 1007530194@qq.com
License-File: LICENSE
Requires-Dist: funpypi
Requires-Dist: tqdm
